MANIFEST.in
README.rst
setup.cfg
setup.py
docs/HISTORY.txt
docs/INSTALL.txt
docs/LICENSE.GPL
docs/LICENSE.txt
src/rt/__init__.py
src/rt.zestreleaser.pypilocal.egg-info/PKG-INFO
src/rt.zestreleaser.pypilocal.egg-info/SOURCES.txt
src/rt.zestreleaser.pypilocal.egg-info/dependency_links.txt
src/rt.zestreleaser.pypilocal.egg-info/entry_points.txt
src/rt.zestreleaser.pypilocal.egg-info/namespace_packages.txt
src/rt.zestreleaser.pypilocal.egg-info/not-zip-safe
src/rt.zestreleaser.pypilocal.egg-info/requires.txt
src/rt.zestreleaser.pypilocal.egg-info/top_level.txt
src/rt/zestreleaser/__init__.py
src/rt/zestreleaser/pypilocal/__init__.py
src/rt/zestreleaser/pypilocal/pypi_local.py
src/rt/zestreleaser/pypilocal/tests/__init__.py
src/rt/zestreleaser/pypilocal/tests/test_copy.py