Metadata-Version: 1.1
Name: rt.zestreleaser.pypilocal
Version: 0.1
Summary: Plugin for zest.releaser to allow putting the created egg in a standard buildout folder
Home-page: https://github.com/RedTurtle/rt.zestreleaser.pypilocal
Author: RedTurtle Technology
Author-email: keul@redturtle.it
License: GPL
Keywords: releaser zest.releaser egg
Platform: UNKNOWN
Classifier: Programming Language :: Python
Classifier: Environment :: Console
Classifier: Environment :: Plugins
Classifier: Intended Audience :: Developers
Classifier: Topic :: Software Development
Classifier: Topic :: System :: Archiving :: Packaging
Classifier: Topic :: System :: Installation/Setup
Classifier: Topic :: Utilities
